pykite/__init__.py
pykite/app.py
pykite/response.py
pykite/http/__init__.py
pykite/http/request.py
pykite/http/response.py
pykite/middleware/__init__.py
pykite/middleware/base.py
pykite-1.0.1.dist-info/LICENSE
pykite-1.0.1.dist-info/METADATA
pykite-1.0.1.dist-info/WHEEL
pykite-1.0.1.dist-info/entry_points.txt
pykite-1.0.1.dist-info/top_level.txt
pykite-1.0.1.dist-info/RECORD
