Metadata-Version: 2.1
Name: pykite
Version: 1.0.1
Summary: A Python-centric micro-framework for building web applications
Home-page: https://github.com/imamhossainroni/pykite
Author: Imam Hossain Roni
Author-email: imamhossainroni95@gmail.com
Project-URL: Bug Tracker, https://github.com/imamhossainroni/pykite/issues
Project-URL: Source Code, https://github.com/imamhossainroni/pykite
Project-URL: Documentation, https://github.com/imamhossainroni/pykite/blob/main/README.md
Project-URL: Icon Image, https://raw.githubusercontent.com/ImamHossainRoni/pykite/main/extras/yellow-kite.png
Keywords: pykite,web framework,micro framework,web applications,Python,HTTP,WSGI
Classifier: Development Status :: 3 - Alpha
Classifier: Intended Audience :: Developers
Classifier: License :: OSI Approved :: MIT License
Classifier: Programming Language :: Python :: 3
Classifier: Programming Language :: Python :: 3.7
Classifier: Programming Language :: Python :: 3.8
Classifier: Programming Language :: Python :: 3.9
Classifier: Topic :: Internet :: WWW/HTTP
Classifier: Topic :: Software Development :: Libraries :: Python Modules
License-File: LICENSE
Requires-Dist: parse
Requires-Dist: werkzeug
